PyDMAP/__init__.py
PyDMAP/df_to_cdf.py
PyDMAP/readwrite_dmap.py
PyDMAP/supermag_tools.py
pydmap-1.1.0.dist-info/METADATA
pydmap-1.1.0.dist-info/WHEEL
pydmap-1.1.0.dist-info/licenses/LICENSE
pydmap-1.1.0.dist-info/RECORD
