Metadata-Version: 2.4
Name: PyDMAP
Version: 1.1.0
Summary: A Python module to read/write binary DataMap, possibly compressed, data files
Project-URL: Homepage, https://gitlab.jhuapl.edu/giuseppe.romeo/pydmap
Project-URL: Issues, https://gitlab.jhuapl.edu/giuseppe.romeo/pydmap/-/issues
Author-email: Giuseppe Romeo <giuseppe.romeo@jhuapl.edu>
License-File: LICENSE
Classifier: License :: OSI Approved :: MIT License
Classifier: Operating System :: OS Independent
Classifier: Programming Language :: Python :: 3
Requires-Python: >=3.8
Requires-Dist: matplotlib
Requires-Dist: numpy
Requires-Dist: pandas
